sockschain/__init__.py
sockschain/__main__.py
sockschain-1.0.0.dist-info/LICENSE
sockschain-1.0.0.dist-info/METADATA
sockschain-1.0.0.dist-info/WHEEL
sockschain-1.0.0.dist-info/entry_points.txt
sockschain-1.0.0.dist-info/top_level.txt
sockschain-1.0.0.dist-info/RECORD
