Metadata-Version: 2.1
Name: sockschain
Version: 1.0.0
Summary: A python module for Chaining of Proxies
Home-page: https://github.com/seanmcfeely/PySocksipyChain
Author: Bjarni R. Einarsson, slight modification by Sean McFeely
Author-email: bre@pagekite.net, mcfeelynaes@gmail.com
License: UNKNOWN
Project-URL: Bug Tracker, https://github.com/seanmcfeely/PySocksipyChain/issues
Keywords: Proxy,Proxy chains
Platform: UNKNOWN
Classifier: Development Status :: 3 - Alpha
Classifier: Intended Audience :: Developers
Classifier: Intended Audience :: Information Technology
Classifier: Programming Language :: Python :: 3
Classifier: License :: OSI Approved :: BSD License
Classifier: Operating System :: OS Independent
Requires-Python: >=3.6
License-File: LICENSE
Requires-Dist: six
